{
	"configurations" : 
	[
		{
			"directories" : 
			[
				{
					"build" : ".",
					"childIndexes" : 
					[
						1
					],
					"jsonFile" : "directory-.-Debug-d0094a50bb2071803777.json",
					"minimumCMakeVersion" : 
					{
						"string" : "3.8"
					},
					"projectIndex" : 0,
					"source" : "."
				},
				{
					"build" : "PhysiCal - C++",
					"jsonFile" : "directory-PhysiCal - C++-Debug-41729eb6d49f119c52ab.json",
					"minimumCMakeVersion" : 
					{
						"string" : "3.8"
					},
					"parentIndex" : 0,
					"projectIndex" : 0,
					"source" : "PhysiCal - C++",
					"targetIndexes" : 
					[
						0
					]
				}
			],
			"name" : "Debug",
			"projects" : 
			[
				{
					"directoryIndexes" : 
					[
						0,
						1
					],
					"name" : "PhysiCal - C++",
					"targetIndexes" : 
					[
						0
					]
				}
			],
			"targets" : 
			[
				{
					"directoryIndex" : 1,
					"id" : "CMakeTarget::@5cf2333f02c2a8473686",
					"jsonFile" : "target-CMakeTarget-Debug-b3733d16dd77c5c4b4c7.json",
					"name" : "CMakeTarget",
					"projectIndex" : 0
				}
			]
		}
	],
	"kind" : "codemodel",
	"paths" : 
	{
		"build" : "C:/Users/Michael/Documents/GitHub/PhysiCal/PhysiCal - C++/out/build/x64-debug",
		"source" : "C:/Users/Michael/Documents/GitHub/PhysiCal/PhysiCal - C++"
	},
	"version" : 
	{
		"major" : 2,
		"minor" : 6
	}
}
